dedupe/variables/__init__.py
dedupe/variables/ilcs.py
dedupe_variable_ilcs-0.1.0.dist-info/LICENSE
dedupe_variable_ilcs-0.1.0.dist-info/METADATA
dedupe_variable_ilcs-0.1.0.dist-info/WHEEL
dedupe_variable_ilcs-0.1.0.dist-info/top_level.txt
dedupe_variable_ilcs-0.1.0.dist-info/RECORD
