Metadata-Version: 2.1
Name: dedupe-variable-ilcs
Version: 0.1.0
Summary: Dedupe variable for Illinois Compiled Statute (ILCS) codes
Home-page: https://github.com/dedupeio/dedupe-variable-ilcs
Author: DataMade
License: The MIT License: http://www.opensource.org/licenses/mit-license.php
Platform: UNKNOWN
Classifier: Development Status :: 3 - Alpha
Classifier: Intended Audience :: Developers
Classifier: Intended Audience :: Science/Research
Classifier: License :: OSI Approved :: MIT License
Classifier: Natural Language :: English
Classifier: Operating System :: MacOS :: MacOS X
Classifier: Operating System :: Microsoft :: Windows
Classifier: Operating System :: POSIX
Classifier: Programming Language :: Python :: 3
Classifier: Topic :: Software Development :: Libraries :: Python Modules
Classifier: Topic :: Scientific/Engineering
Classifier: Topic :: Scientific/Engineering :: Information Analysis
Requires-Dist: ilcs-parser
Requires-Dist: parseratorvariable
Provides-Extra: tests
Requires-Dist: pytest ; extra == 'tests'
Requires-Dist: parserator ; extra == 'tests'
